rxncon/__init__.py
rxncon/core/__init__.py
rxncon/core/contingency.py
rxncon/core/effector.py
rxncon/core/reaction.py
rxncon/core/rxncon_system.py
rxncon/core/spec.py
rxncon/core/state.py
rxncon/input/__init__.py
rxncon/input/excel_book/__init__.py
rxncon/input/excel_book/excel_book.py
rxncon/input/quick/__init__.py
rxncon/input/quick/quick.py
rxncon/input/sbtab/__init__.py
rxncon/input/sbtab/definitions.tsv
rxncon/input/sbtab/rxncon_Definition.tsv
rxncon/input/sbtab/sbtab.py
rxncon/input/shared/__init__.py
rxncon/input/shared/contingency_list.py
rxncon/input/shared/reaction_preprocess.py
rxncon/simulation/__init__.py
rxncon/simulation/boolean/__init__.py
rxncon/simulation/boolean/boolean_model.py
rxncon/simulation/boolean/boolnet_from_boolean_model.py
rxncon/simulation/ode/__init__.py
rxncon/simulation/ode/ode.py
rxncon/simulation/ode/polynomials.py
rxncon/simulation/rule_based/__init__.py
rxncon/simulation/rule_based/bngl_from_rule_based_model.py
rxncon/simulation/rule_based/rule_based_model.py
rxncon/test/__init__.py
rxncon/test/core/__init__.py
rxncon/test/core/test_effector.py
rxncon/test/core/test_reaction.py
rxncon/test/core/test_rxncon_system.py
rxncon/test/core/test_spec.py
rxncon/test/core/test_state.py
rxncon/test/input/__init__.py
rxncon/test/input/excel_book/__init__.py
rxncon/test/input/excel_book/additional_modifiers.xls
rxncon/test/input/excel_book/additional_rxns.xls
rxncon/test/input/excel_book/missing_necessary_sheet.xls
rxncon/test/input/excel_book/missing_unnecessary_sheet.xls
rxncon/test/input/excel_book/shuffled_columns.xls
rxncon/test/input/excel_book/test_excel_book.py
rxncon/test/input/quick/__init__.py
rxncon/test/input/quick/test_quick.py
rxncon/test/input/sbtab/Tiger_et_al_TableS1_SBtab_ContingencyID.tsv
rxncon/test/input/sbtab/Tiger_et_al_TableS1_SBtab_Gene.tsv
rxncon/test/input/sbtab/Tiger_et_al_TableS1_SBtab_Reaction.tsv
rxncon/test/input/sbtab/Tiger_et_al_TableS1_SBtab_ReactionID.tsv
rxncon/test/input/sbtab/__init__.py
rxncon-2.0b19.dist-info/LICENSE.txt
rxncon-2.0b19.dist-info/METADATA
rxncon-2.0b19.dist-info/WHEEL
rxncon-2.0b19.dist-info/top_level.txt
rxncon-2.0b19.dist-info/RECORD
